mdformat_gfm/__init__.py
mdformat_gfm/_gfm.py
mdformat_gfm/_mdformat_plugin.py
mdformat_gfm/_mdit_gfm_autolink_plugin.py
mdformat_gfm/_text_inline_rule.py
mdformat_gfm-0.4.0.dist-info/entry_points.txt
mdformat_gfm-0.4.0.dist-info/LICENSE
mdformat_gfm-0.4.0.dist-info/WHEEL
mdformat_gfm-0.4.0.dist-info/METADATA
mdformat_gfm-0.4.0.dist-info/RECORD
