Metadata-Version: 2.3
Name: mdformat-gfm
Version: 0.4.0
Summary: Mdformat plugin for GitHub Flavored Markdown compatibility
Keywords: mdformat,markdown,formatter,gfm
Author-email: Taneli Hukkinen <hukkin@users.noreply.github.com>
Requires-Python: >=3.9
Classifier: Topic :: Documentation
Classifier: Topic :: Text Processing :: Markup
Requires-Dist: mdformat >=0.7.5,<0.8.0
Requires-Dist: markdown-it-py
Requires-Dist: mdit-py-plugins >=0.2.0
Requires-Dist: mdformat-tables >=0.4.0
Project-URL: Homepage, https://github.com/hukkin/mdformat-gfm
